{"content":[{"id":"2a118c02","elType":"section","settings":{"padding":{"unit":"px","top":"30","right":"30","bottom":"30","left":"30","isLinked":true}},"elements":[{"id":"67e96026","elType":"column","settings":{"_column_size":100},"elements":[{"id":"51997fe5","elType":"widget","settings":{"image":{"id":10182,"url":"https:\/\/library.elementor.com\/wp-content\/uploads\/2019\/01\/glasses-1.png"},"image_size":"full","width":{"unit":"%","size":40},"space":{"unit":"%","size":100},"_padding":{"unit":"px","top":"0","right":"0","bottom":"20","left":"0","isLinked":false},"_padding_mobile":{"unit":"px","top":"0","right":"0","bottom":"0","left":"0","isLinked":false},"_animation":"slideInDown","animation_duration":"fast"},"elements":[],"widgetType":"image"},{"id":"5438c9b6","elType":"widget","settings":{"title":"Put On Your Fine Print Glasses:","align":"center","title_color":"#000000","typography_typography":"custom","typography_font_family":"Josefin Slab","typography_font_size":{"unit":"px","size":30},"typography_font_size_mobile":{"unit":"px","size":20},"typography_font_weight":"bold"},"elements":[],"widgetType":"heading"},{"id":"2c410a9c","elType":"widget","settings":{"title":"Important Details Ahead","align":"center","title_color":"#000000","typography_typography":"custom","typography_font_family":"Josefin Slab","typography_font_size":{"unit":"px","size":30},"typography_font_size_mobile":{"unit":"px","size":20},"typography_font_weight":"bold","_margin":{"unit":"px","top":"-10","right":"0","bottom":"0","left":"0","isLinked":false}},"elements":[],"widgetType":"heading"},{"id":"58380f1","elType":"widget","settings":{"editor":"<p>Lorem ipsum dolor sit amet, consectetuer adipiscing elit, sed diam nonummy nibh euismod tincidunt ut laoreet dolore magna aliquam erat volutpat. Ut wisi enim ad minim veniam, quis nostrud exerci tation ullamcorper suscipit lobortis nisl ut aliquip.<\/p>","align":"center","text_color":"#666666","typography_typography":"custom","typography_font_family":"Josefin Slab","typography_font_size":{"unit":"px","size":15},"typography_font_size_mobile":{"unit":"px","size":15}},"elements":[],"widgetType":"text-editor"},{"id":"23df8b49","elType":"widget","settings":{"text":"Got it! Thanks.","align":"center","size":"md","typography_typography":"custom","typography_font_family":"Josefin Slab","typography_font_size":{"unit":"px","size":18},"button_text_color":"#f2f2f2","background_color":"#f5a2a2","hover_color":"#000000","border_radius":{"unit":"px","top":"50","right":"50","bottom":"50","left":"50","isLinked":true},"__dynamic__":{"link":"[elementor-tag id=\"01552ca\" name=\"popup\" settings=\"%7B%22action%22%3A%22close%22%7D\"]"}},"elements":[],"widgetType":"button"}],"isInner":false}],"isInner":false}],"page_settings":{"width":{"unit":"px","size":500},"horizontal_position":"left","vertical_position":"bottom","background_background":"classic","background_color":"#f2f2f2","box_shadow_box_shadow":{"horizontal":7,"vertical":-5,"blur":32,"spread":0,"color":"rgba(0,0,0,0.09)"},"overlay_background_color":"rgba(0,0,0,0)","close_button_color":"#000000","close_button_background_color":"rgba(0,0,0,0)"}}